pinkyclawd/__init__.py
pinkyclawd/events.py
pinkyclawd/agent/__init__.py
pinkyclawd/agent/base.py
pinkyclawd/agent/build.py
pinkyclawd/agent/explore.py
pinkyclawd/agent/plan.py
pinkyclawd/agent/registry.py
pinkyclawd/bus/__init__.py
pinkyclawd/bus/event_types.py
pinkyclawd/bus/global_bus.py
pinkyclawd/cli/__init__.py
pinkyclawd/cli/conversation.py
pinkyclawd/cli/main.py
pinkyclawd/commands/__init__.py
pinkyclawd/commands/builtins.py
pinkyclawd/commands/registry.py
pinkyclawd/config/__init__.py
pinkyclawd/config/keybind.py
pinkyclawd/config/paths.py
pinkyclawd/config/settings.py
pinkyclawd/config/storage.py
pinkyclawd/config/theme.py
pinkyclawd/constants/__init__.py
pinkyclawd/constants/models.py
pinkyclawd/constants/rlm.py
pinkyclawd/constants/tools.py
pinkyclawd/core/__init__.py
pinkyclawd/core/container.py
pinkyclawd/core/instance.py
pinkyclawd/core/state.py
pinkyclawd/lsp/__init__.py
pinkyclawd/lsp/client.py
pinkyclawd/lsp/language.py
pinkyclawd/lsp/operations.py
pinkyclawd/lsp/server.py
pinkyclawd/mcp/__init__.py
pinkyclawd/mcp/auth.py
pinkyclawd/mcp/client.py
pinkyclawd/mcp/oauth.py
pinkyclawd/mcp/transport.py
pinkyclawd/provider/__init__.py
pinkyclawd/provider/anthropic.py
pinkyclawd/provider/base.py
pinkyclawd/provider/openai.py
pinkyclawd/provider/registry.py
pinkyclawd/rlm/__init__.py
pinkyclawd/rlm/archive.py
pinkyclawd/rlm/auto_inject.py
pinkyclawd/rlm/context.py
pinkyclawd/rlm/display.py
pinkyclawd/rlm/embedding.py
pinkyclawd/rlm/extraction.py
pinkyclawd/rlm/graph.py
pinkyclawd/rlm/graph_json.py
pinkyclawd/rlm/handler.py
pinkyclawd/rlm/ingestion.py
pinkyclawd/rlm/retrieve.py
pinkyclawd/rlm/search.py
pinkyclawd/rlm/summarize.py
pinkyclawd/rlm/traversal.py
pinkyclawd/server/__init__.py
pinkyclawd/server/app.py
pinkyclawd/server/routes/__init__.py
pinkyclawd/server/routes/chat.py
pinkyclawd/server/routes/mcp.py
pinkyclawd/server/routes/session.py
pinkyclawd/session/__init__.py
pinkyclawd/session/export.py
pinkyclawd/session/manager.py
pinkyclawd-0.2.0.dist-info/METADATA
pinkyclawd-0.2.0.dist-info/WHEEL
pinkyclawd-0.2.0.dist-info/entry_points.txt
pinkyclawd-0.2.0.dist-info/licenses/LICENSE
pinkyclawd-0.2.0.dist-info/RECORD
