Metadata-Version: 2.4
Name: pinkyclawd
Version: 0.2.0
Summary: Production-grade TUI for AI-assisted development with RLM context management
Project-URL: Homepage, https://github.com/tekcin/PinkyClawd
Project-URL: Documentation, https://github.com/tekcin/PinkyClawd#readme
Project-URL: Repository, https://github.com/tekcin/PinkyClawd
Project-URL: Issues, https://github.com/tekcin/PinkyClawd/issues
Author-email: Michael Thornton <tekcin@yahoo.com>
License: MIT
License-File: LICENSE
Keywords: ai,anthropic,claude,coding,development,gpt,llm,openai,rlm,terminal,tui
Classifier: Development Status :: 4 - Beta
Classifier: Environment :: Console
Classifier: Intended Audience :: Developers
Classifier: License :: OSI Approved :: MIT License
Classifier: Operating System :: OS Independent
Classifier: Programming Language :: Python :: 3
Classifier: Programming Language :: Python :: 3.11
Classifier: Programming Language :: Python :: 3.12
Classifier: Topic :: Software Development
Classifier: Topic :: Terminals
Requires-Python: >=3.11
Requires-Dist: anthropic>=0.25.0
Requires-Dist: httpx>=0.27.0
Requires-Dist: openai>=1.0.0
Requires-Dist: python-dotenv>=1.0.0
Requires-Dist: rich>=13.0.0
Requires-Dist: textual>=0.50.0
Requires-Dist: tiktoken>=0.6.0
Provides-Extra: all
Requires-Dist: mypy>=1.8.0; extra == 'all'
Requires-Dist: pytest-asyncio>=0.23.0; extra == 'all'
Requires-Dist: pytest>=8.0.0; extra == 'all'
Requires-Dist: ruff>=0.3.0; extra == 'all'
Provides-Extra: dev
Requires-Dist: mypy>=1.8.0; extra == 'dev'
Requires-Dist: pytest-asyncio>=0.23.0; extra == 'dev'
Requires-Dist: pytest>=8.0.0; extra == 'dev'
Requires-Dist: ruff>=0.3.0; extra == 'dev'
